LICENSE.txt
MANIFEST.in
README.md
setup.cfg
setup.py
localstudio/__init__.py
localstudio/cli.py
localstudio/debug.py
localstudio/event_stream.py
localstudio/job_settings.py
localstudio.egg-info/PKG-INFO
localstudio.egg-info/SOURCES.txt
localstudio.egg-info/dependency_links.txt
localstudio.egg-info/entry_points.txt
localstudio.egg-info/requires.txt
localstudio.egg-info/top_level.txt
localstudio/app/__init__.py
localstudio/app/api.py
localstudio/app/config.py
localstudio/app/mixin.py
localstudio/app/swagger.py
localstudio/app/blueprints/__init__.py
localstudio/app/blueprints/assets/__init__.py
localstudio/app/blueprints/assets/resources.py
localstudio/app/blueprints/auth/__init__.py
localstudio/app/blueprints/auth/resources.py
localstudio/app/blueprints/breakdown/__init__.py
localstudio/app/blueprints/breakdown/resources.py
localstudio/app/blueprints/comments/__init__.py
localstudio/app/blueprints/comments/resources.py
localstudio/app/blueprints/crud/__init__.py
localstudio/app/blueprints/crud/asset_instance.py
localstudio/app/blueprints/crud/attachment_file.py
localstudio/app/blueprints/crud/base.py
localstudio/app/blueprints/crud/comments.py
localstudio/app/blueprints/crud/custom_action.py
localstudio/app/blueprints/crud/day_off.py
localstudio/app/blueprints/crud/department.py
localstudio/app/blueprints/crud/entity.py
localstudio/app/blueprints/crud/entity_link.py
localstudio/app/blueprints/crud/entity_type.py
localstudio/app/blueprints/crud/event.py
localstudio/app/blueprints/crud/file_status.py
localstudio/app/blueprints/crud/metadata_descriptor.py
localstudio/app/blueprints/crud/milestone.py
localstudio/app/blueprints/crud/news.py
localstudio/app/blueprints/crud/notification.py
localstudio/app/blueprints/crud/organisation.py
localstudio/app/blueprints/crud/output_file.py
localstudio/app/blueprints/crud/output_type.py
localstudio/app/blueprints/crud/person.py
localstudio/app/blueprints/crud/playlist.py
localstudio/app/blueprints/crud/preview_background_file.py
localstudio/app/blueprints/crud/preview_file.py
localstudio/app/blueprints/crud/project.py
localstudio/app/blueprints/crud/project_status.py
localstudio/app/blueprints/crud/schedule_item.py
